ampalibe/__init__.py
ampalibe/__main__.py
ampalibe/cmd.py
ampalibe/constant.py
ampalibe/core.py
ampalibe/decorators.py
ampalibe/logger.py
ampalibe/messenger.py
ampalibe/model.py
ampalibe/payload.py
ampalibe/source.py
ampalibe/tools.py
ampalibe/ui.py
ampalibe/utils.py
ampalibe-1.1.9.data/scripts/ampalibe
ampalibe-1.1.9.data/scripts/ampalibe.bat
ampalibe-1.1.9.dist-info/LICENSE
ampalibe-1.1.9.dist-info/METADATA
ampalibe-1.1.9.dist-info/WHEEL
ampalibe-1.1.9.dist-info/top_level.txt
ampalibe-1.1.9.dist-info/RECORD
