Metadata-Version: 2.1
Name: ampalibe
Version: 1.1.9
Summary: Ampalibe is a lightweight Python framework for building Facebook Messenger bots faster.
Home-page: https://github.com/iTeam-S/ampalibe
Author: iTeam-$
Author-email: contact@iteam-s.mg
License: UNKNOWN
Project-URL: Bug Tracker, https://github.com/iTeam-S/ampalibe/issues
Platform: UNKNOWN
Classifier: Programming Language :: Python :: 3
Classifier: Programming Language :: Python :: 3.7
Classifier: Programming Language :: Python :: 3.8
Classifier: Programming Language :: Python :: 3.9
Classifier: Programming Language :: Python :: 3.10
Classifier: Programming Language :: Python :: 3.11
Classifier: License :: OSI Approved :: MIT License
Classifier: Operating System :: OS Independent
Requires-Python: >=3.7
Requires-Dist: fastapi
Requires-Dist: uvicorn
Requires-Dist: retry
Requires-Dist: requests
Requires-Dist: colorama
Requires-Dist: requests-toolbelt
Requires-Dist: watchdog (!=2.2.0)
Requires-Dist: aiocron
Requires-Dist: tinydb
